kaggle_waggle/__init__.py
kaggle_waggle/api_client.py
kaggle_waggle/cli.py
kaggle_waggle/configuration.py
kaggle_waggle/rest.py
kaggle_waggle/api/__init__.py
kaggle_waggle/api/kaggle_api.py
kaggle_waggle/api/kaggle_api_extended.py
kaggle_waggle/models/__init__.py
kaggle_waggle/models/api_blob_type.py
kaggle_waggle/models/collaborator.py
kaggle_waggle/models/create_inbox_file_request.py
kaggle_waggle/models/dataset_column.py
kaggle_waggle/models/dataset_new_request.py
kaggle_waggle/models/dataset_new_version_request.py
kaggle_waggle/models/dataset_update_settings_request.py
kaggle_waggle/models/error.py
kaggle_waggle/models/kaggle_models_extended.py
kaggle_waggle/models/kernel_push_request.py
kaggle_waggle/models/license.py
kaggle_waggle/models/model_instance_new_version_request.py
kaggle_waggle/models/model_instance_update_request.py
kaggle_waggle/models/model_new_instance_request.py
kaggle_waggle/models/model_new_request.py
kaggle_waggle/models/model_update_request.py
kaggle_waggle/models/result.py
kaggle_waggle/models/start_blob_upload_request.py
kaggle_waggle/models/start_blob_upload_response.py
kaggle_waggle/models/upload_file.py
kaggle_waggle/test/__init__.py
kaggle_waggle/test/test_authenticate.py
kaggle_waggle-1.6.12a8.dist-info/METADATA
kaggle_waggle-1.6.12a8.dist-info/WHEEL
kaggle_waggle-1.6.12a8.dist-info/entry_points.txt
kaggle_waggle-1.6.12a8.dist-info/licenses/LICENSE
kaggle_waggle-1.6.12a8.dist-info/RECORD
