Metadata-Version: 2.3
Name: kaggle_waggle
Version: 1.6.12a8
Summary: Access Kaggle resources anywhere
Project-URL: Homepage, https://github.com/Kaggle/kaggle-api
Project-URL: Issues, https://github.com/Kaggle/kaggle-api/issues
Author-email: Kaggle <support@kaggle.com>
License:                                  Apache License
License-File: LICENSE
Keywords: API,Kaggle
Classifier: License :: OSI Approved :: Apache Software License
Classifier: Operating System :: OS Independent
Classifier: Programming Language :: Python :: 3
Requires-Python: >=3.7
Requires-Dist: bleach
Requires-Dist: certifi>=14.05.14
Requires-Dist: charset-normalizer
Requires-Dist: idna
Requires-Dist: python-dateutil>=2.5.3
Requires-Dist: python-slugify
Requires-Dist: requests
Requires-Dist: setuptools>=21.0.0
Requires-Dist: six>=1.10
Requires-Dist: text-unidecode
Requires-Dist: tqdm
Requires-Dist: urllib3>=1.15.1
Requires-Dist: webencodings
